dojo/__init__.py
dojo/cli.py
dojo/dataset.py
dojo/dojo.py
dojo/error_handler.py
dojo/errors.py
dojo/datasets/__init__.py
dojo/datasets/storage_keys.py
dojo/datasets/union.py
dojo/transforms/__init__.py
dojo/transforms/compact.py
dojo/transforms/conform_to_schema.py
dojo/transforms/de_key.py
dojo/transforms/distinct.py
dojo/transforms/key_by.py
dojo/transforms/left_outer_join.py
dojo/transforms/random_repartition.py
dojo/transforms/read_from_json.py
dojo/transforms/read_from_static.py
dojo/transforms/union.py
dojo/transforms/validate_schema.py
dojo/transforms/write_to_json.py
dojo/transforms/write_to_static.py
dojo-0.1.0.dist-info/DESCRIPTION.rst
dojo-0.1.0.dist-info/METADATA
dojo-0.1.0.dist-info/RECORD
dojo-0.1.0.dist-info/WHEEL
dojo-0.1.0.dist-info/entry_points.txt
dojo-0.1.0.dist-info/metadata.json
dojo-0.1.0.dist-info/top_level.txt
tests/datasets/__init__.py
tests/datasets/test_storage_keys.py
tests/datasets/test_union.py
tests/transforms/__init__.py
tests/transforms/test_compact.py
tests/transforms/test_conform_to_schema.py
tests/transforms/test_de_key.py
tests/transforms/test_dictinct.py
tests/transforms/test_key_by.py
tests/transforms/test_left_outer_join.py
tests/transforms/test_random_repartition.py
tests/transforms/test_read_from_json.py
tests/transforms/test_read_from_static.py
tests/transforms/test_union.py
tests/transforms/test_validate_schema.py
tests/transforms/test_write_to_json.py
tests/transforms/test_write_to_static.py
