Metadata-Version: 2.0
Name: dojo
Version: 0.1.0
Summary: A framework for building and running your data platform.
Home-page: https://www.dataup.me/
Author: Data Up
Author-email: dojo@dataup.me
License: UNKNOWN
Platform: UNKNOWN
Requires-Dist: apache-beam[gcp]
Requires-Dist: google-cloud-storage (==1.2.0)
Requires-Dist: grpcio (==1.4.0)
Requires-Dist: six (==1.10.0)
Requires-Dist: stored
Requires-Dist: click
Requires-Dist: jsonschema
Requires-Dist: python-dateutil
